DomNom/__init__.py
DomNom/router.py
DomNom/server.py
tests/__init__.py
tests/test_router.py
tests/test_server.py
DomNom-0.2.0.dist-info/METADATA
DomNom-0.2.0.dist-info/WHEEL
DomNom-0.2.0.dist-info/top_level.txt
DomNom-0.2.0.dist-info/RECORD
