Metadata-Version: 2.1
Name: DomNom
Version: 0.2.0
Summary: A Python package for routing and web application management.
Home-page: https://github.com/yourusername/DomNom
Author: Hiralal Singh
Author-email: hiralals221@gmail.com
Classifier: Programming Language :: Python :: 3
Classifier: License :: OSI Approved :: MIT License
Classifier: Operating System :: OS Independent
Requires-Python: >=3.6
Requires-Dist: Flask>=2.0
Requires-Dist: requests>=2.26
Provides-Extra: dev
Requires-Dist: tox>=3.0; extra == "dev"
Requires-Dist: black>=22.0; extra == "dev"
Requires-Dist: flake8>=4.0; extra == "dev"
